tutordisable_public_signup/__about__.py
tutordisable_public_signup/__init__.py
tutordisable_public_signup/plugin.py
tutordisable_public_signup/patches/.gitignore
tutordisable_public_signup/templates/disable-public-signup/apps/.gitignore
tutordisable_public_signup/templates/disable-public-signup/build/.gitignore
tutordisable_public_signup/templates/disable-public-signup/tasks/lms/.gitignore
tutor_contrib_disable_public_signup-1.0.0.dist-info/METADATA
tutor_contrib_disable_public_signup-1.0.0.dist-info/WHEEL
tutor_contrib_disable_public_signup-1.0.0.dist-info/entry_points.txt
tutor_contrib_disable_public_signup-1.0.0.dist-info/licenses/LICENSE.txt
tutor_contrib_disable_public_signup-1.0.0.dist-info/RECORD
